.coveragerc
.hgignore
.hgtags
CHANGES.rst
README.rst
bootstrap.py
buildout.cfg
pytest.ini
setup.py
tox.ini
src/gocept/__init__.py
src/gocept.zcapatch.egg-info/PKG-INFO
src/gocept.zcapatch.egg-info/SOURCES.txt
src/gocept.zcapatch.egg-info/dependency_links.txt
src/gocept.zcapatch.egg-info/namespace_packages.txt
src/gocept.zcapatch.egg-info/not-zip-safe
src/gocept.zcapatch.egg-info/requires.txt
src/gocept.zcapatch.egg-info/top_level.txt
src/gocept/zcapatch/__init__.py
src/gocept/zcapatch/patches.py
src/gocept/zcapatch/tests/__init__.py
src/gocept/zcapatch/tests/test_patches.py