Metadata-Version: 1.1
Name: gocept.zcapatch
Version: 1.1
Summary: Test helpers to temporarily alter zope.component registrations
